phasefield/InspectSharp.py
phasefield/__init__.py
phasefield/auxfun.py
phasefield/external.py
phasefield/ob_frac.cc
phasefield/stepper.py
phasefield/tnnmg.cc
phasefield/ufl_dict.py
phasefield/ufl_phasefield.py
phasefield/useDune.py
phasefield/useFenics.py
phasefield-1.0.1.dist-info/LICENSE.md
phasefield-1.0.1.dist-info/METADATA
phasefield-1.0.1.dist-info/WHEEL
phasefield-1.0.1.dist-info/top_level.txt
phasefield-1.0.1.dist-info/RECORD
