Metadata-Version: 2.1
Name: phasefield
Version: 1.0.1
Summary: Interface problem solver based on the phase-field methodology
Home-page: https://gitlab.dune-project.org/dune-fem/phasefield
Author: Matthew Collins and Andreas Dedner
Author-email: a.s.dedner@warwick.ac.uk
License: UNKNOWN
Platform: UNKNOWN
Classifier: Programming Language :: Python :: 3
Classifier: License :: OSI Approved :: GNU Affero General Public License v3 or later (AGPLv3+)
Classifier: Operating System :: OS Independent
Requires-Dist: UFL (==2017.1.0)
